mmlibrary/__init__.py
mmlibrary-0.0.1.dist-info/METADATA
mmlibrary-0.0.1.dist-info/WHEEL
mmlibrary-0.0.1.dist-info/top_level.txt
mmlibrary-0.0.1.dist-info/RECORD
